{
  "id": 15,
  "title": "Inazuma Eleven Fan-Cut",
  "show_title": "Inazuma Eleven Fan-Cut",
  "torrents": [],
  "seasons": [
    {
      "id": 28,
      "season_number": 1,
      "title": "Saison 1",
      "torrents": [
        {
          "nyaa_id": 1554720,
          "nyaa_url": "https://nyaa.si/view/1554720",
          "title": "[Livaï] Inazuma Eleven (Fan-kai) - Saisons 1/2 - 1080p.MULTI.VF/VOSTFR.x264",
          "torrent_url": "https://nyaa.si/download/1554720.torrent",
          "magnet": "magnet:?xt=urn:btih:e7d82377db02546c18f1bffbe50fbc73b1b0eb57&dn=%5BLiva%C3%AF%5D%20Inazuma%20Eleven%20%28Fan-kai%29%20-%20Saisons%201%2F2%20-%201080p.MULTI.VF%2FVOSTFR.x264&tr=http%3A%2F%2Fnyaa.tracker.wf%3A7777%2Fannounce&tr=udp%3A%2F%2Fopen.stealth.si%3A80%2Fannounce&tr=udp%3A%2F%2Ftracker.opentrackr.org%3A1337%2Fannounce&tr=udp%3A%2F%2Fexodus.desync.com%3A6969%2Fannounce&tr=udp%3A%2F%2Ftracker.torrent.eu.org%3A451%2Fannounce",
          "infohash": "e7d82377db02546c18f1bffbe50fbc73b1b0eb57",
          "size": "24.0 GiB",
          "pub_date": "2022-07-20 14:23",
          "seeders": 6
        }
      ],
      "episodes": [
        {
          "id": 279,
          "episode_number": 1,
          "title": "Le Collège Raimon",
          "aired": "2020-01-21",
          "torrents": [],
          "paths": [
            {
              "infohash": "e7d82377db02546c18f1bffbe50fbc73b1b0eb57",
              "path": "Inazuma Eleven (Fan-kai) [Livai]/Saison 1/[Livai] Inazuma Eleven 01 (Fan-kai) - Le Collège Raimon - 1080p.MULTI.x264.mkv"
            }
          ]
        },
        {
          "id": 280,
          "episode_number": 2,
          "title": "La Malédiction",
          "aired": "2020-01-25",
          "torrents": [],
          "paths": [
            {
              "infohash": "e7d82377db02546c18f1bffbe50fbc73b1b0eb57",
              "path": "Inazuma Eleven (Fan-kai) [Livai]/Saison 1/[Livai] Inazuma Eleven 02 (Fan-kai) - La Malédiction - 1080p.MULTI.x264.mkv"
            }
          ]
        },
        {
          "id": 277,
          "episode_number": 3,
          "title": "Qualifications pour le Football Frontier",
          "aired": "2020-01-25",
          "torrents": [],
          "paths": [
            {
              "infohash": "e7d82377db02546c18f1bffbe50fbc73b1b0eb57",
              "path": "Inazuma Eleven (Fan-kai) [Livai]/Saison 1/[Livai] Inazuma Eleven 03 (Fan-kai) - Qualifications pour le Football Frontier - 1080p.MULTI.x264.mkv"
            }
          ]
        },
        {
          "id": 281,
          "episode_number": 4,
          "title": "Match revanche",
          "aired": "2020-05-27",
          "torrents": [],
          "paths": [
            {
              "infohash": "e7d82377db02546c18f1bffbe50fbc73b1b0eb57",
              "path": "Inazuma Eleven (Fan-kai) [Livai]/Saison 1/[Livai] Inazuma Eleven 04 (Fan-Kai) - Match revanche - 1080p.MULTI.x264.mkv"
            }
          ]
        },
        {
          "id": 275,
          "episode_number": 5,
          "title": "Les Joueurs de foot ninjas",
          "aired": "2020-10-19",
          "torrents": [],
          "paths": [
            {
              "infohash": "e7d82377db02546c18f1bffbe50fbc73b1b0eb57",
              "path": "Inazuma Eleven (Fan-kai) [Livai]/Saison 1/[Livai] Inazuma Eleven 05 (Fan-kai) - Les Joueurs de foot ninjas - 1080p.MULTI.x264.mkv"
            }
          ]
        },
        {
          "id": 282,
          "episode_number": 6,
          "title": "La muraille infinie",
          "aired": "2020-10-22",
          "torrents": [],
          "paths": [
            {
              "infohash": "e7d82377db02546c18f1bffbe50fbc73b1b0eb57",
              "path": "Inazuma Eleven (Fan-kai) [Livai]/Saison 1/[Livai] Inazuma Eleven 06 (Fan-kai) - La Muraille Infinie - 1080p.MULTI.x264.mkv"
            }
          ]
        },
        {
          "id": 278,
          "episode_number": 7,
          "title": "Le Triangle Z",
          "aired": "2020-10-25",
          "torrents": [],
          "paths": [
            {
              "infohash": "e7d82377db02546c18f1bffbe50fbc73b1b0eb57",
              "path": "Inazuma Eleven (Fan-kai) [Livai]/Saison 1/[Livai] Inazuma Eleven 07 (Fan-kai) - Le Triangle Z - 1080p.MULTI.x264.mkv"
            }
          ]
        },
        {
          "id": 276,
          "episode_number": 8,
          "title": "Combat contre les dieux",
          "aired": "2020-11-08",
          "torrents": [],
          "paths": [
            {
              "infohash": "e7d82377db02546c18f1bffbe50fbc73b1b0eb57",
              "path": "Inazuma Eleven (Fan-kai) [Livai]/Saison 1/[Livaï] Inazuma Eleven 08 (Fan-kai) - Combat contre les dieux - 1080p.MULTI.x264.mkv"
            }
          ]
        }
      ]
    },
    {
      "id": 27,
      "season_number": 2,
      "title": "Saison 2",
      "torrents": [
        {
          "nyaa_id": 1554720,
          "nyaa_url": "https://nyaa.si/view/1554720",
          "title": "[Livaï] Inazuma Eleven (Fan-kai) - Saisons 1/2 - 1080p.MULTI.VF/VOSTFR.x264",
          "torrent_url": "https://nyaa.si/download/1554720.torrent",
          "magnet": "magnet:?xt=urn:btih:e7d82377db02546c18f1bffbe50fbc73b1b0eb57&dn=%5BLiva%C3%AF%5D%20Inazuma%20Eleven%20%28Fan-kai%29%20-%20Saisons%201%2F2%20-%201080p.MULTI.VF%2FVOSTFR.x264&tr=http%3A%2F%2Fnyaa.tracker.wf%3A7777%2Fannounce&tr=udp%3A%2F%2Fopen.stealth.si%3A80%2Fannounce&tr=udp%3A%2F%2Ftracker.opentrackr.org%3A1337%2Fannounce&tr=udp%3A%2F%2Fexodus.desync.com%3A6969%2Fannounce&tr=udp%3A%2F%2Ftracker.torrent.eu.org%3A451%2Fannounce",
          "infohash": "e7d82377db02546c18f1bffbe50fbc73b1b0eb57",
          "size": "24.0 GiB",
          "pub_date": "2022-07-20 14:23",
          "seeders": 6
        }
      ],
      "episodes": [
        {
          "id": 265,
          "episode_number": 9,
          "title": "Les Extraterrestres débarquent",
          "aired": "2021-05-12",
          "torrents": [],
          "paths": [
            {
              "infohash": "e7d82377db02546c18f1bffbe50fbc73b1b0eb57",
              "path": "Inazuma Eleven (Fan-kai) [Livai]/Saison 2/[Livaï] Inazuma Eleven 09 (Fan-kai) - Les Extraterrestres débarquent - 1080p.MULTI.x264.mkv"
            }
          ]
        },
        {
          "id": 274,
          "episode_number": 10,
          "title": "Le Prince des Neiges",
          "aired": "2021-05-15",
          "torrents": [],
          "paths": [
            {
              "infohash": "e7d82377db02546c18f1bffbe50fbc73b1b0eb57",
              "path": "Inazuma Eleven (Fan-kai) [Livai]/Saison 2/[Livaï] Inazuma Eleven 10 (Fan-kai) - Le Prince des neiges - 1080p.MULTI.x264.mkv"
            }
          ]
        },
        {
          "id": 268,
          "episode_number": 11,
          "title": "L'Assaut d'Epsilon",
          "aired": "2021-05-20",
          "torrents": [],
          "paths": [
            {
              "infohash": "e7d82377db02546c18f1bffbe50fbc73b1b0eb57",
              "path": "Inazuma Eleven (Fan-kai) [Livai]/Saison 2/[Livaï] Inazuma Eleven 11 (Fan-kai) - L’Assaut d'Epsilon - 1080p.MULTI.x264.mkv"
            }
          ]
        },
        {
          "id": 273,
          "episode_number": 12,
          "title": "La Contre-attaque de la Royale",
          "aired": "2021-05-21",
          "torrents": [],
          "paths": [
            {
              "infohash": "e7d82377db02546c18f1bffbe50fbc73b1b0eb57",
              "path": "Inazuma Eleven (Fan-kai) [Livai]/Saison 2/[Livaï] Inazuma Eleven 12 (Fan-kai) - La Contre-attaque de la Royal - 1080p.MULTI.x264.mkv"
            }
          ]
        },
        {
          "id": 272,
          "episode_number": 13,
          "title": "Les Manigances de Dvalin",
          "aired": "2021-06-01",
          "torrents": [],
          "paths": [
            {
              "infohash": "e7d82377db02546c18f1bffbe50fbc73b1b0eb57",
              "path": "Inazuma Eleven (Fan-kai) [Livai]/Saison 2/[Livaï] Inazuma Eleven 13 (Fan-kai) - Les manigances de Dvalin - 1080p.MULTI.x264.mkv"
            }
          ]
        },
        {
          "id": 271,
          "episode_number": 14,
          "title": "L'autre Main Céleste",
          "aired": "2022-01-10",
          "torrents": [],
          "paths": [
            {
              "infohash": "e7d82377db02546c18f1bffbe50fbc73b1b0eb57",
              "path": "Inazuma Eleven (Fan-kai) [Livai]/Saison 2/[Livaï] Inazuma Eleven 14 (Fan-kai) - L'autre Main Céleste - 1080p.MULTI.x264.mkv"
            }
          ]
        },
        {
          "id": 266,
          "episode_number": 15,
          "title": "L'Attaquant de feu",
          "aired": "2022-03-10",
          "torrents": [],
          "paths": [
            {
              "infohash": "e7d82377db02546c18f1bffbe50fbc73b1b0eb57",
              "path": "Inazuma Eleven (Fan-kai) [Livai]/Saison 2/[Livaï] Inazuma Eleven 15 (Fan-kai) - L'Attaquant de Feu - 1080p.MULTI.x264.mkv"
            }
          ]
        },
        {
          "id": 270,
          "episode_number": 16,
          "title": "Diamond Dust et Prominence",
          "aired": "2022-07-07",
          "torrents": [],
          "paths": [
            {
              "infohash": "e7d82377db02546c18f1bffbe50fbc73b1b0eb57",
              "path": "Inazuma Eleven (Fan-kai) [Livai]/Saison 2/[Livaï] Inazuma Eleven 16 (Fan-kai) - Diamond Dust et Prominence - 1080p.MULTI.x264.mkv"
            }
          ]
        },
        {
          "id": 269,
          "episode_number": 17,
          "title": "Genesis",
          "aired": "2022-07-11",
          "torrents": [],
          "paths": [
            {
              "infohash": "e7d82377db02546c18f1bffbe50fbc73b1b0eb57",
              "path": "Inazuma Eleven (Fan-kai) [Livai]/Saison 2/[Livaï] Inazuma Eleven 17 (Fan-kai) - Genesis - 1080p.MULTI.x264.mkv"
            }
          ]
        },
        {
          "id": 267,
          "episode_number": 18,
          "title": "Les Empereurs Noirs",
          "aired": "2022-07-12",
          "torrents": [],
          "paths": [
            {
              "infohash": "e7d82377db02546c18f1bffbe50fbc73b1b0eb57",
              "path": "Inazuma Eleven (Fan-kai) [Livai]/Saison 2/[Livaï] Inazuma Eleven 18 (Fan-kai) - Les Empereurs Noirs - 1080p.MULTI.x264.mkv"
            }
          ]
        }
      ]
    },
    {
      "id": 26,
      "season_number": 3,
      "title": "Saison 3",
      "torrents": [],
      "episodes": [
        {
          "id": 254,
          "episode_number": 19,
          "title": "La naissance d'Inazuma Japon",
          "aired": "2023-04-17",
          "torrents": [
            {
              "nyaa_id": 1661574,
              "nyaa_url": "https://nyaa.si/view/1661574",
              "title": "[Livai] Inazuma Eleven 19 (Fan-kai) - La naissance d'Inazuma Japon - 720p.MULTI.x264",
              "torrent_url": "https://nyaa.si/download/1661574.torrent",
              "magnet": "magnet:?xt=urn:btih:37aadeb72da2f5d1236ba8e113f0d23da314096e&dn=%5BLivai%5D%20Inazuma%20Eleven%2019%20%28Fan-kai%29%20-%20La%20naissance%20d%27Inazuma%20Japon%20-%20720p.MULTI.x264&tr=http%3A%2F%2Fnyaa.tracker.wf%3A7777%2Fannounce&tr=udp%3A%2F%2Fopen.stealth.si%3A80%2Fannounce&tr=udp%3A%2F%2Ftracker.opentrackr.org%3A1337%2Fannounce&tr=udp%3A%2F%2Fexodus.desync.com%3A6969%2Fannounce&tr=udp%3A%2F%2Ftracker.torrent.eu.org%3A451%2Fannounce",
              "infohash": "37aadeb72da2f5d1236ba8e113f0d23da314096e",
              "size": "2.3 GiB",
              "pub_date": "2023-04-16 20:15",
              "seeders": 5
            }
          ],
          "paths": [
            {
              "infohash": "37aadeb72da2f5d1236ba8e113f0d23da314096e",
              "path": "[Livaï] Inazuma Eleven 19 (Fan-kai) - La naissance d'Inazuma Japon - 720p.MULTI.x264.mkv"
            }
          ]
        },
        {
          "id": 264,
          "episode_number": 20,
          "title": "Les Néo Japon",
          "aired": "2023-04-18",
          "torrents": [
            {
              "nyaa_id": 1661972,
              "nyaa_url": "https://nyaa.si/view/1661972",
              "title": "[Livai] Inazuma Eleven 20 (Fan-kai) - Les Néo Japon - 720p.MULTI.x264",
              "torrent_url": "https://nyaa.si/download/1661972.torrent",
              "magnet": "magnet:?xt=urn:btih:fe0e9190fd34811674969c88e46ea5d1b5cf3e17&dn=%5BLivai%5D%20Inazuma%20Eleven%2020%20%28Fan-kai%29%20-%20Les%20N%C3%A9o%20Japon%20-%20720p.MULTI.x264&tr=http%3A%2F%2Fnyaa.tracker.wf%3A7777%2Fannounce&tr=udp%3A%2F%2Fopen.stealth.si%3A80%2Fannounce&tr=udp%3A%2F%2Ftracker.opentrackr.org%3A1337%2Fannounce&tr=udp%3A%2F%2Fexodus.desync.com%3A6969%2Fannounce&tr=udp%3A%2F%2Ftracker.torrent.eu.org%3A451%2Fannounce",
              "infohash": "fe0e9190fd34811674969c88e46ea5d1b5cf3e17",
              "size": "1.1 GiB",
              "pub_date": "2023-04-17 19:17",
              "seeders": 6
            }
          ],
          "paths": [
            {
              "infohash": "fe0e9190fd34811674969c88e46ea5d1b5cf3e17",
              "path": "[Livaï] Inazuma Eleven 20 (Fan-kai) - Les Néo Japon - 720p.MULTI.x264.mkv"
            }
          ]
        },
        {
          "id": 262,
          "episode_number": 21,
          "title": "Les Dragons de Feu",
          "aired": null,
          "torrents": [
            {
              "nyaa_id": 1663316,
              "nyaa_url": "https://nyaa.si/view/1663316",
              "title": "[Livai] Inazuma Eleven 21 (Fan-kai) - Les Dragons de Feu - 720p.MULTI.x264",
              "torrent_url": "https://nyaa.si/download/1663316.torrent",
              "magnet": "magnet:?xt=urn:btih:17c0a7f519773091705808564a056aa1f7a7559c&dn=%5BLivai%5D%20Inazuma%20Eleven%2021%20%28Fan-kai%29%20-%20Les%20Dragons%20de%20Feu%20-%20720p.MULTI.x264&tr=http%3A%2F%2Fnyaa.tracker.wf%3A7777%2Fannounce&tr=udp%3A%2F%2Fopen.stealth.si%3A80%2Fannounce&tr=udp%3A%2F%2Ftracker.opentrackr.org%3A1337%2Fannounce&tr=udp%3A%2F%2Fexodus.desync.com%3A6969%2Fannounce&tr=udp%3A%2F%2Ftracker.torrent.eu.org%3A451%2Fannounce",
              "infohash": "17c0a7f519773091705808564a056aa1f7a7559c",
              "size": "2.1 GiB",
              "pub_date": "2023-04-21 18:59",
              "seeders": 4
            }
          ],
          "paths": [
            {
              "infohash": "17c0a7f519773091705808564a056aa1f7a7559c",
              "path": "[Livaï] Inazuma Eleven 21 (Fan-kai) - Les Dragons de Feu - 720p.MULTI.x264.mkv"
            }
          ]
        },
        {
          "id": 257,
          "episode_number": 22,
          "title": "Les Knights of Queen",
          "aired": null,
          "torrents": [
            {
              "nyaa_id": 1663689,
              "nyaa_url": "https://nyaa.si/view/1663689",
              "title": "[Livaï] Inazuma Eleven 22 (Fan-kai) - Les Knights of Queen - 720p.MULTI.x264",
              "torrent_url": "https://nyaa.si/download/1663689.torrent",
              "magnet": "magnet:?xt=urn:btih:c56316903ae379af0b788dc234b1f88b3e656af1&dn=%5BLiva%C3%AF%5D%20Inazuma%20Eleven%2022%20%28Fan-kai%29%20-%20Les%20Knights%20of%20Queen%20-%20720p.MULTI.x264&tr=http%3A%2F%2Fnyaa.tracker.wf%3A7777%2Fannounce&tr=udp%3A%2F%2Fopen.stealth.si%3A80%2Fannounce&tr=udp%3A%2F%2Ftracker.opentrackr.org%3A1337%2Fannounce&tr=udp%3A%2F%2Fexodus.desync.com%3A6969%2Fannounce&tr=udp%3A%2F%2Ftracker.torrent.eu.org%3A451%2Fannounce",
              "infohash": "c56316903ae379af0b788dc234b1f88b3e656af1",
              "size": "1.4 GiB",
              "pub_date": "2023-04-22 19:44",
              "seeders": 6
            }
          ],
          "paths": [
            {
              "infohash": "c56316903ae379af0b788dc234b1f88b3e656af1",
              "path": "[Livaï] Inazuma Eleven 22 (Fan-kai) - Les Knights of Queen - 720p.MULTI.x264.mkv"
            }
          ]
        },
        {
          "id": 259,
          "episode_number": 23,
          "title": "Emprise",
          "aired": "2023-10-16",
          "torrents": [
            {
              "nyaa_id": 1730199,
              "nyaa_url": "https://nyaa.si/view/1730199",
              "title": "[Livai] Inazuma Eleven 23 (Fan-kai) - Emprise - 720p.MULTI.x264",
              "torrent_url": "https://nyaa.si/download/1730199.torrent",
              "magnet": "magnet:?xt=urn:btih:4f4a4e416f47e3f5cfaaaf348ec3917b921f9d0f&dn=%5BLivai%5D%20Inazuma%20Eleven%2023%20%28Fan-kai%29%20-%20Emprise%20-%20720p.MULTI.x264&tr=http%3A%2F%2Fnyaa.tracker.wf%3A7777%2Fannounce&tr=udp%3A%2F%2Fopen.stealth.si%3A80%2Fannounce&tr=udp%3A%2F%2Ftracker.opentrackr.org%3A1337%2Fannounce&tr=udp%3A%2F%2Fexodus.desync.com%3A6969%2Fannounce&tr=udp%3A%2F%2Ftracker.torrent.eu.org%3A451%2Fannounce",
              "infohash": "4f4a4e416f47e3f5cfaaaf348ec3917b921f9d0f",
              "size": "2.1 GiB",
              "pub_date": "2023-10-16 20:30",
              "seeders": 5
            }
          ],
          "paths": [
            {
              "infohash": "4f4a4e416f47e3f5cfaaaf348ec3917b921f9d0f",
              "path": "[Livaï] Inazuma Eleven 23 (Fan-kai) - Emprise - 720p.MULTI.x264.mkv"
            }
          ]
        },
        {
          "id": 256,
          "episode_number": 24,
          "title": "Le dernier coup d'envoi du Phénix",
          "aired": "2023-10-17",
          "torrents": [
            {
              "nyaa_id": 1730654,
              "nyaa_url": "https://nyaa.si/view/1730654",
              "title": "[Livai] Inazuma Eleven 24 (Fan-kai) - Le dernier coup d'envoi du Phénix  - 720p.MULTI.x264",
              "torrent_url": "https://nyaa.si/download/1730654.torrent",
              "magnet": "magnet:?xt=urn:btih:8e8331065d96af25e17ba91c9af6968d72459ba3&dn=%5BLivai%5D%20Inazuma%20Eleven%2024%20%28Fan-kai%29%20-%20Le%20dernier%20coup%20d%27envoi%20du%20Ph%C3%A9nix%20%20-%20720p.MULTI.x264&tr=http%3A%2F%2Fnyaa.tracker.wf%3A7777%2Fannounce&tr=udp%3A%2F%2Fopen.stealth.si%3A80%2Fannounce&tr=udp%3A%2F%2Ftracker.opentrackr.org%3A1337%2Fannounce&tr=udp%3A%2F%2Fexodus.desync.com%3A6969%2Fannounce&tr=udp%3A%2F%2Ftracker.torrent.eu.org%3A451%2Fannounce",
              "infohash": "8e8331065d96af25e17ba91c9af6968d72459ba3",
              "size": "1.4 GiB",
              "pub_date": "2023-10-17 20:14",
              "seeders": 6
            }
          ],
          "paths": [
            {
              "infohash": "8e8331065d96af25e17ba91c9af6968d72459ba3",
              "path": "[Livaï] Inazuma Eleven 24 (Fan-kai) - Le dernier coup d'envoi du Phénix  - 720p.MULTI.x264.mkv"
            }
          ]
        },
        {
          "id": 260,
          "episode_number": 25,
          "title": "La Contre Attaque Catenaccio",
          "aired": "2023-10-18",
          "torrents": [
            {
              "nyaa_id": 1731011,
              "nyaa_url": "https://nyaa.si/view/1731011",
              "title": "[Livai] Inazuma Eleven 25 (Fan-kai) - La Contre-Attaque Catenaccio - 720p.MULTI.x264",
              "torrent_url": "https://nyaa.si/download/1731011.torrent",
              "magnet": "magnet:?xt=urn:btih:45b9b939c0ac9dba401a73110d5122e53fb1d3a0&dn=%5BLivai%5D%20Inazuma%20Eleven%2025%20%28Fan-kai%29%20-%20La%20Contre-Attaque%20Catenaccio%20-%20720p.MULTI.x264&tr=http%3A%2F%2Fnyaa.tracker.wf%3A7777%2Fannounce&tr=udp%3A%2F%2Fopen.stealth.si%3A80%2Fannounce&tr=udp%3A%2F%2Ftracker.opentrackr.org%3A1337%2Fannounce&tr=udp%3A%2F%2Fexodus.desync.com%3A6969%2Fannounce&tr=udp%3A%2F%2Ftracker.torrent.eu.org%3A451%2Fannounce",
              "infohash": "45b9b939c0ac9dba401a73110d5122e53fb1d3a0",
              "size": "1.4 GiB",
              "pub_date": "2023-10-18 19:26",
              "seeders": 6
            }
          ],
          "paths": [
            {
              "infohash": "45b9b939c0ac9dba401a73110d5122e53fb1d3a0",
              "path": "[Livaï] Inazuma Eleven 25 (Fan-kai) - La Contre-Attaque Catenaccio - 720p.MULTI.x264.mkv"
            }
          ]
        },
        {
          "id": 261,
          "episode_number": 26,
          "title": "La légende de Liocott",
          "aired": "2024-10-10",
          "torrents": [
            {
              "nyaa_id": 1883550,
              "nyaa_url": "https://nyaa.si/view/1883550",
              "title": "[Livaï] Inazuma Eleven 26 (Fan-kai) - La légende de Liocott - 720p.MULTI.x264",
              "torrent_url": "https://nyaa.si/download/1883550.torrent",
              "magnet": "magnet:?xt=urn:btih:965fc7eb604d2638a56d0ac07842f665ded504de&dn=%5BLiva%C3%AF%5D%20Inazuma%20Eleven%2026%20%28Fan-kai%29%20-%20La%20l%C3%A9gende%20de%20Liocott%20-%20720p.MULTI.x264&tr=http%3A%2F%2Fnyaa.tracker.wf%3A7777%2Fannounce&tr=udp%3A%2F%2Fopen.stealth.si%3A80%2Fannounce&tr=udp%3A%2F%2Ftracker.opentrackr.org%3A1337%2Fannounce&tr=udp%3A%2F%2Fexodus.desync.com%3A6969%2Fannounce&tr=udp%3A%2F%2Ftracker.torrent.eu.org%3A451%2Fannounce",
              "infohash": "965fc7eb604d2638a56d0ac07842f665ded504de",
              "size": "1.8 GiB",
              "pub_date": "2024-10-10 19:26",
              "seeders": 5
            }
          ],
          "paths": [
            {
              "infohash": "965fc7eb604d2638a56d0ac07842f665ded504de",
              "path": "[Livaï] Inazuma Eleven 26 (Fan-kai) - La légende de Liocott - 720p.MULTI.x264.mkv"
            }
          ]
        },
        {
          "id": 258,
          "episode_number": 27,
          "title": "La Face cachée des Rois du Football",
          "aired": "2024-10-11",
          "torrents": [
            {
              "nyaa_id": 1884048,
              "nyaa_url": "https://nyaa.si/view/1884048",
              "title": "[Livaï] Inazuma Eleven 27 (Fan-kai) - La Face cachée des Rois du Football - 720p.MULTI.x264",
              "torrent_url": "https://nyaa.si/download/1884048.torrent",
              "magnet": "magnet:?xt=urn:btih:6d63ed4836215690f86a5bacbcc6a1f9e87f85a3&dn=%5BLiva%C3%AF%5D%20Inazuma%20Eleven%2027%20%28Fan-kai%29%20-%20La%20Face%20cach%C3%A9e%20des%20Rois%20du%20Football%20-%20720p.MULTI.x264&tr=http%3A%2F%2Fnyaa.tracker.wf%3A7777%2Fannounce&tr=udp%3A%2F%2Fopen.stealth.si%3A80%2Fannounce&tr=udp%3A%2F%2Ftracker.opentrackr.org%3A1337%2Fannounce&tr=udp%3A%2F%2Fexodus.desync.com%3A6969%2Fannounce&tr=udp%3A%2F%2Ftracker.torrent.eu.org%3A451%2Fannounce",
              "infohash": "6d63ed4836215690f86a5bacbcc6a1f9e87f85a3",
              "size": "1.4 GiB",
              "pub_date": "2024-10-11 19:24",
              "seeders": 5
            }
          ],
          "paths": [
            {
              "infohash": "6d63ed4836215690f86a5bacbcc6a1f9e87f85a3",
              "path": "[Livaï] Inazuma Eleven 27 (Fan-kai) - La Face cachée des Rois du Football - 720p.MULTI.x264.mkv"
            }
          ]
        },
        {
          "id": 253,
          "episode_number": 28,
          "title": "Les joueurs de dernière génération",
          "aired": "2024-10-12",
          "torrents": [
            {
              "nyaa_id": 1884578,
              "nyaa_url": "https://nyaa.si/view/1884578",
              "title": "[Livaï] Inazuma Eleven 28 (Fan-kai) - Les joueurs de dernière génération - 720p.MULTI.x264",
              "torrent_url": "https://nyaa.si/download/1884578.torrent",
              "magnet": "magnet:?xt=urn:btih:bf22f471f828e59cf7110ec755f3a5b2194a4b78&dn=%5BLiva%C3%AF%5D%20Inazuma%20Eleven%2028%20%28Fan-kai%29%20-%20Les%20joueurs%20de%20derni%C3%A8re%20g%C3%A9n%C3%A9ration%20-%20720p.MULTI.x264&tr=http%3A%2F%2Fnyaa.tracker.wf%3A7777%2Fannounce&tr=udp%3A%2F%2Fopen.stealth.si%3A80%2Fannounce&tr=udp%3A%2F%2Ftracker.opentrackr.org%3A1337%2Fannounce&tr=udp%3A%2F%2Fexodus.desync.com%3A6969%2Fannounce&tr=udp%3A%2F%2Ftracker.torrent.eu.org%3A451%2Fannounce",
              "infohash": "bf22f471f828e59cf7110ec755f3a5b2194a4b78",
              "size": "1.1 GiB",
              "pub_date": "2024-10-12 19:33",
              "seeders": 4
            }
          ],
          "paths": [
            {
              "infohash": "bf22f471f828e59cf7110ec755f3a5b2194a4b78",
              "path": "[Livaï] Inazuma Eleven 28 (Fan-kai) - Les joueurs de dernière génération - 720p.MULTI.x264.mkv"
            }
          ]
        },
        {
          "id": 255,
          "episode_number": 29,
          "title": "Duel au sommet",
          "aired": null,
          "torrents": [
            {
              "nyaa_id": 1895263,
              "nyaa_url": "https://nyaa.si/view/1895263",
              "title": "[Livaï] Inazuma Eleven 29 (Fan-kai) - Duel au sommet  - 720p.MULTI.x264",
              "torrent_url": "https://nyaa.si/download/1895263.torrent",
              "magnet": "magnet:?xt=urn:btih:b38e4987bcdf7ef77c16e8d120b7ceaed145bb67&dn=%5BLiva%C3%AF%5D%20Inazuma%20Eleven%2029%20%28Fan-kai%29%20-%20Duel%20au%20sommet%20%20-%20720p.MULTI.x264&tr=http%3A%2F%2Fnyaa.tracker.wf%3A7777%2Fannounce&tr=udp%3A%2F%2Fopen.stealth.si%3A80%2Fannounce&tr=udp%3A%2F%2Ftracker.opentrackr.org%3A1337%2Fannounce&tr=udp%3A%2F%2Fexodus.desync.com%3A6969%2Fannounce&tr=udp%3A%2F%2Ftracker.torrent.eu.org%3A451%2Fannounce",
              "infohash": "b38e4987bcdf7ef77c16e8d120b7ceaed145bb67",
              "size": "2.6 GiB",
              "pub_date": "2024-11-04 20:15",
              "seeders": 5
            }
          ],
          "paths": [
            {
              "infohash": "b38e4987bcdf7ef77c16e8d120b7ceaed145bb67",
              "path": "[Livaï] Inazuma Eleven 29 (Fan-kai) - Duel au sommet  - 720p.MULTI.x264.mkv"
            }
          ]
        },
        {
          "id": 263,
          "episode_number": 30,
          "title": "Le coup d'envoi de l'avenir",
          "aired": "2024-11-05",
          "torrents": [
            {
              "nyaa_id": 1895680,
              "nyaa_url": "https://nyaa.si/view/1895680",
              "title": "[Livaï] Inazuma Eleven 30 (Fan-kai) - Le coup d'envoi de l'avenir - 720p.MULTI.x264",
              "torrent_url": "https://nyaa.si/download/1895680.torrent",
              "magnet": "magnet:?xt=urn:btih:8c61d17aafb639328463abc435902c44b74ad998&dn=%5BLiva%C3%AF%5D%20Inazuma%20Eleven%2030%20%28Fan-kai%29%20-%20Le%20coup%20d%27envoi%20de%20l%27avenir%20-%20720p.MULTI.x264&tr=http%3A%2F%2Fnyaa.tracker.wf%3A7777%2Fannounce&tr=udp%3A%2F%2Fopen.stealth.si%3A80%2Fannounce&tr=udp%3A%2F%2Ftracker.opentrackr.org%3A1337%2Fannounce&tr=udp%3A%2F%2Fexodus.desync.com%3A6969%2Fannounce&tr=udp%3A%2F%2Ftracker.torrent.eu.org%3A451%2Fannounce",
              "infohash": "8c61d17aafb639328463abc435902c44b74ad998",
              "size": "850.6 MiB",
              "pub_date": "2024-11-05 20:27",
              "seeders": 6
            }
          ],
          "paths": [
            {
              "infohash": "8c61d17aafb639328463abc435902c44b74ad998",
              "path": "[Livaï] Inazuma Eleven 30 (Fan-kai) - Le coup d'envoi de l'avenir - 720p.MULTI.x264.mkv"
            }
          ]
        }
      ]
    }
  ]
}